LICENSE
MANIFEST.in
README.md
setup.py
django_pathfinder_statcrunch/__init__.py
django_pathfinder_statcrunch/admin.py
django_pathfinder_statcrunch/apps.py
django_pathfinder_statcrunch/models.py
django_pathfinder_statcrunch/tests.py
django_pathfinder_statcrunch/urls.py
django_pathfinder_statcrunch/views.py
django_pathfinder_statcrunch.egg-info/PKG-INFO
django_pathfinder_statcrunch.egg-info/SOURCES.txt
django_pathfinder_statcrunch.egg-info/dependency_links.txt
django_pathfinder_statcrunch.egg-info/top_level.txt
django_pathfinder_statcrunch/migrations/0001_initial.py
django_pathfinder_statcrunch/migrations/0002_auto_20201102_1851.py
django_pathfinder_statcrunch/migrations/0003_auto_20201102_1853.py
django_pathfinder_statcrunch/migrations/__init__.py
django_pathfinder_statcrunch/templates/django_pathfinder_statcrunch/sidebar.html
django_pathfinder_statcrunch/templates/django_pathfinder_statcrunch/adminlte/list_reports.html
django_pathfinder_statcrunch/templates/django_pathfinder_statcrunch/adminlte/view_report.html