Metadata-Version: 2.1
Name: django-pathfinder-statcrunch
Version: 0.0.3
Summary: A reusable Django application using the Krypted Gaming template.
Home-page: https://github.com/porowns/django-pathfinder-statcrunch
Author: porowns
Author-email: porowns@gmail.com
License: MIT License
Platform: UNKNOWN
Classifier: Environment :: Web Environment
Classifier: Framework :: Django
Classifier: Intended Audience :: Developers
Classifier: License :: OSI Approved :: MIT License
Classifier: Operating System :: OS Independent
Classifier: Programming Language :: Python
Classifier: Programming Language :: Python :: 3.5
Classifier: Programming Language :: Python :: 3.6
Classifier: Topic :: Internet :: WWW/HTTP
Classifier: Topic :: Internet :: WWW/HTTP :: Dynamic Content
